group09_lab5_part3/alu_group09.v
module alu(DATA1,DATA2,RESULT,SELECT);
	//Input port declaration
	//DATA 1, DATA2 8 bit inputs
	//SELECT 3 bit input
	input signed [7:0] DATA1,DATA2;
	input [2:0] SELECT;

	//Output port declatation
	//RESULT,forw,addition are 8 bit outputs
	//RESULT= final output of the ALU depending on the select input
	//forwout = output of forwardunit module
	//addout = output of addunit module
	//andout = output of andunit module
	//orout = output of orunit module
	output signed [7:0] RESULT,forwout,addout,andout,orout;

	//Instantiate all the functional units
	forwardunit f1(DATA2,SELECT,forwout);
	addunit a1(DATA1,DATA2,SELECT,addout);
	andunit and1(DATA1,DATA2,SELECT,andout);
	orunit or1(DATA1,DATA2,SELECT,orout);

	//Instantiate the mux to get the final output "RESULT"
	mux m1(forwout,addout,andout,orout,SELECT,RESULT);

endmodule
	
//FOWARD FUNCTION MODULE

module forwardunit(DATA2,SELECT,RESULT);
	//Input port declaration
	//DATA1,DATA2 - 8 bit signed inputs

	input [7:0] DATA2;
	input [2:0] SELECT;

	//Output port declaration
	//RESULT - 8 bit signed output = DATA2
	output  signed[7:0] RESULT;

	//Generate RESULT whenever DATA1 or DATA2 change
	//always @(SELECT,DATA2)
	 assign #1 RESULT=  DATA2;
 	
endmodule

//ADD FUNCTION MODULE

module addunit (DATA1,DATA2,SELECT,RESULT);
	//Input port declaration
	//DATA1,DATA2 - 8 bit signed inputs
	
	input signed [7:0] DATA1,DATA2;
	input [2:0] SELECT;

	//Output port declaration
	//RESULT - 8 bit signed output = DATA1 + DATA2
	output  signed [7:0] RESULT;
	
	//Generate RESULT whenever DATA1 or DATA2 change
	//always @(SELECT,DATA1,DATA2)
	 assign #2 RESULT =  ( DATA1 + DATA2) ;
endmodule

//AND FUNCTION MODULE

module andunit (DATA1,DATA2,SELECT,RESULT);
	//Input port declaration
	//DATA1,DATA2 - 8 bit signed inputs
	input signed [7:0] DATA1,DATA2;
	input [2:0] SELECT;

	//Output port declaration
	//RESULT - 8 bit signed output = DATA1 & DATA2
	output   [7:0] RESULT;
	
	//Generate RESULT whenever DATA1 or DATA2 change
	//always @(DATA1,DATA2)
	 assign #1 RESULT = ( DATA1 & DATA2) ;
endmodule

//OR FUNCTION MODULE

module orunit (DATA1,DATA2,SELECT,RESULT);
	//Input port declaration
	//DATA1,DATA2 - 8 bit signed inputs
	input signed [7:0] DATA1,DATA2;
	input [2:0] SELECT;
	
	//Output port declaration
	//RESULT - 8 bit signed output = DATA1 | DATA2
	output [7:0] RESULT;

	//Generate RESULT whenever DATA1 or DATA2 change
	//always @(DATA1,DATA2)
	assign #1 RESULT =  ( DATA1 | DATA2) ;
endmodule

	
//MULTIPLEXER MODULE (4 X 1)

module mux(in0,in1,in2,in3,sel,result);
	//Input port declaration
	//in0 = forwardunit output
	//in1 = addunit output
	//in2 = andunit output
	//in3 = orunit output
	//sel = 3 bit select input
	input signed [7:0] in0,in1,in2,in3;
	input [2:0] sel;

	//Output port declaration
	//result = final result of the mux depending on sel
	output reg signed[7:0] result;

	//Update the result whenever in0,in1,in2,in3 or sel change
	always @(in0,in1,in2,in3,sel)
	begin
		case (sel)
			3'b000:  result = in0;
			3'b001:  result = in1;
			3'b010:  result = in2;
			3'b011:  result = in3;
			default: result = -1;
			
		endcase
	end
endmodule

group09_lab5_part3/regfile_group09.v
//CO224 VERILOG LAB 5- PART 2
// 8 x 8 REGISTER FILE
//GROUP 09

//TOP LEVEL STIMULUS MODULE
/*
module test;
	//Input variable declaration
	//WRITEDATA = 8 Bit data input
	//WRITEREG = 3 bit write address
	//READREG1 & READREG2 = 3 bit read addresses
	//CLK = Clock signal
	//WRITEENABLE = Write enable signal (When WRITE =1 at positive clk edge) 
	//RESET = Reset registers signal (When RESET =1 at positive clk edge) 
	reg signed [7:0] WRITEDATA;
	reg [2:0] WRITEREG,READREG1,READREG2;
	reg CLK,WRITEENABLE,RESET;

	//Output variable declaration
	//REGOUT1 , REGOUT2 = 8 bit data stored in registers
	wire signed [7:0] REGOUT1,REGOUT2;
	
	//Monitor changes in variables
	initial 
	$monitor($time," CLK %d RESET %d WRITE %d OUT1ADDRESS %d OUT2ADDRESS %d OUT1=%d OUT2 = %d",CLK,RESET,WRITEENABLE,READREG1,READREG2,REGOUT1,REGOUT2);

	//Instantiate reg_file module
	reg_file r1(WRITEDATA,REGOUT1,REGOUT2,WRITEREG,READREG1,READREG2,WRITEENABLE,CLK,RESET);

	//Generate the CLK signal with period 10
	
	initial
	begin
		CLK=1'b1;
		forever #5 CLK =~CLK;
	end

	//Finish the simulation after 100 time units
	initial
	begin
		#100 $finish;
	end


        //WRITE VARIABLE
	initial
	begin
		WRITEENABLE = 0;
		#5 WRITEENABLE = 1;
	       	#40 WRITEENABLE = 0;
		#20 WRITEENABLE = 1;	
	
	end
	
	//RESET VARIABLE
	initial
	begin
		RESET = 1;
		#15 RESET = 0;
		#50 RESET = 1;
	        #10 RESET = 0;
	
	end

	//WRITING INPUTS (WRITEDATA AND WRITEREG)
	initial
	begin
		WRITEDATA = -23;
	       	WRITEREG = 3;
		#25;
		WRITEDATA = 35;
		WRITEREG = 6;
		#10;
		WRITEDATA = 20;
		WRITEREG = 2;
		#5
		WRITEDATA = 45;
		WRITEREG = 2;
		#20;
		WRITEDATA = 5;
		WRITEREG = 0;
		#25;
		WRITEDATA = 12;
		WRITEREG = 7;

	end

	//READING REGISTER VARIABLES
	initial
	begin
		READREG1 = 0;
		READREG2 = 3;
		#25;
	        READREG1 = 6;
		#10;
		READREG2 = 2;
		#20;
		READREG1 = 0;	
		#25;
		READREG2 = 7;
	
	end
	
	//Generate the wave file
	initial
	begin
		
		$dumpfile("reg.vcd");
		$dumpvars(0,test);
	end

endmodule


//REGISTER FILE MODULE
*/
module reg_file(IN,OUT1,OUT2,INADDRESS,OUT1ADDRESS,OUT2ADDRESS,WRITE,CLK,RESET);

	//INPUT PORT DECLARATION
	//IN = 8 bit write data
	//INADDRESS = 3 bit write address
	//OUT1ADDRESS, OUT2ADDRESS = 3 bit read addresses
	
	input signed [7:0] IN;
	input [2:0] INADDRESS,OUT1ADDRESS,OUT2ADDRESS;
	input CLK,WRITE,RESET;

	//OUTPUT PORT DECLARATION
	//OUT1,OUT2 = 8 bit read data
	output signed [7:0] OUT1,OUT2;
	
	//Register type array of 8 elements to store 8 bit register data
	reg signed [7:0] regfile [0:7];

	//Generate the wave file which includes the values stored in each register	
	//Implemented for testing purposes
	initial
	begin 
		$dumpfile("cpu_wavedata.vcd");
		for(i=0;i<8;i++)
			$dumpvars(1,regfile[i]);

	end

	//READ REGISTERS ASYNCHRONOUSLY
	//OUT1 AND OUT2 MUST CHANGE IF OUT1ADDRESS,OUT2ADDRESS OR THE VALUES IN RELEVANT REGISTERS CHANGE
	//OUT1 AND OUT2 MUST CHANGE AFTER A DELAY OF 2,UNTIL IT CHANGES IT SHOULD DISPLAY THE PREVIOUS VALUE STORED IN THEM
	//DELAY = 2
	assign #2 OUT1 =  regfile[OUT1ADDRESS];
	assign #2 OUT2 =  regfile[OUT2ADDRESS];
	//WRITE TO REGISTER AT THE POSITIVE EDGE OF CLK AND WHEN WRITE=1 AND RESET = 0
	//DELAY = 1
	always @(posedge CLK)
	begin
		if (WRITE && RESET == 1'b0)
		/*begin
			regfile[INADDRESS] <= #1 IN;
		end*/
			#1 regfile[INADDRESS] =  IN;
	end
	 
	//RESET THE REGISTERS WHEN RESET=1 AND CLK IS IN POSITIVE EDGE
	//DELAY = 1
	integer i;
	always @(posedge CLK)
	begin
		if (RESET)
			#1
			begin
				for(i=0;i<8;i=i+1)
					/*begin
						regfile [i] <= #1 0;
					end*/
						regfile[i]  = 0;
			end
	end


endmodule

group09_lab5_part3/cpu_group09.v
//CO224 VERILOG LAB 5- PART 3
// CPU file
//GROUP 09


module cpu_tb;

    reg CLK, RESET;
    wire [31:0] PC;
    wire [31:0] INSTRUCTION;
    
    
    /* 
    ------------------------
     SIMPLE INSTRUCTION MEM
    ------------------------
    */
    
    // TODO: Initialize an array of registers (8x1024) named 'instr_mem' to be used as instruction memory
    reg [7:0] instr_mem [0:1024];

    
    initial
    begin
        // Initialize instruction memory with the set of instructions you need execute on CPU
        
        // METHOD 1: manually loading instructions to instr_mem
        //{instr_mem[10'd3], instr_mem[10'd2], instr_mem[10'd1], instr_mem[10'd0]} = 32'b00000000000001000000000000000101;
        //{instr_mem[10'd7], instr_mem[10'd6], instr_mem[10'd5], instr_mem[10'd4]} = 32'b00000000000000100000000000001001;
        //{instr_mem[10'd11], instr_mem[10'd10], instr_mem[10'd9], instr_mem[10'd8]} = 32'b00000010000001100000010000000010;
        
        // METHOD 2: loading instr_mem content from instr_mem.mem file
        $readmemb("instr_mem.mem", instr_mem);
    end
    // TODO: Create combinational logic to support CPU instruction fetching, given the Program Counter(PC) value 
    //       (make sure you include the delay for instruction fetching here)
    assign #2 INSTRUCTION[7:0] = instr_mem[PC];
    assign #2 INSTRUCTION[15:8] = instr_mem[PC+1];
    assign #2 INSTRUCTION[23:16] = instr_mem[PC+2];
    assign #2 INSTRUCTION[31:24]= instr_mem[PC+3];
    	
    initial
	   // PC_CURRENT=0;
	    //$monitor($time," %b %b %b %b",instr_mem[4],instr_mem[5],instr_mem[6],instr_mem[7]);
    	    $monitor($time," PC  %d INSTRUCTION IN MEMORY %b",PC,INSTRUCTION);
			//$monitor($time,"\t%d\t%d\t%d\t%d\t%d\t%d\t%d", regfile[0], regfile[1],regfile[2],regfile[3],regfile[4],regfile[5],regfile[6],regfile[7],);
    /* 
    -----
     CPU
    -----
    */
    cpu mycpu(PC, INSTRUCTION, CLK, RESET);

    initial
    begin
    
        // generate files needed to plot the waveform using GTKWave
        $dumpfile("cpu_wavedata.vcd");
		$dumpvars(0, cpu_tb);
        
        CLK = 1'b0;
        RESET = 1'b1;
	#5 RESET = 1'b0;
        
        // TODO: Reset the CPU (by giving a pulse to RESET signal) to start the program execution
        
        // finish simulation after some time
        #200
        $finish;
        
    end
    
    // clock signal generation
    always
        #4 CLK = ~CLK;
        

endmodule

//CPU module
module cpu(PC, INSTRUCTION, CLK, RESET);
	//Input and output port decleration
    input CLK, RESET;
    input   [31:0] INSTRUCTION; //32 bit instruction.
    output [31:0] PC;			//PC 32 bit address for the instruction memory.
    //decleration of ports  to regfile and alu
	input [7:0] WRITEDATA;
	input [2:0] opcode;
    reg WRITE;
    output [7:0] REGOUT1, REGOUT2; 	//for regfile two outputs.
	output [7:0] temp2, temp3; 		//outputs for muxes.
	reg [2:0] temp_sel;				//for decoded output
	//assigning the opcode.
	assign opcode = INSTRUCTION[31:24];
	reg comp_flag, imm_flag;
	wire [7:0] compliment2;
	//reset the pc
	PC_reset res(RESET, PC, CLK);
	//Instantiate the register.
    reg_file reg1(WRITEDATA, REGOUT1, REGOUT2, INSTRUCTION[18:16], INSTRUCTION[10:8], INSTRUCTION[2:0], 1'b1, CLK, RESET);
	//Decoding the opcode and assigning them to temp_sel
	assign #1 compliment2 =  ~REGOUT2 + 1;
	always @(opcode)
	begin
	case (opcode)
		3'b000: begin
		  		temp_sel <= #1 3'b000; 
				comp_flag <= #1 0; 
				imm_flag <= #1 1;
			end
		3'b001: begin
				temp_sel <= #1 3'b000;
				comp_flag <= #1 0; 
				imm_flag <= #1 0;
			end 
		3'b010: begin
				temp_sel <= #1 3'b001;
				comp_flag <= #1 0; 
				imm_flag <= #1 0;
			end 
		3'b011: begin
				temp_sel <= #1 3'b001;
				comp_flag <= #1 1; 
				imm_flag <= #1 0;
		end 
		3'b100: begin
				temp_sel <= #1 3'b010;
				comp_flag <= #1 0; 
				imm_flag <= #1 0;
		end 
		3'b101: begin
				temp_sel <= #1 3'b011;
				comp_flag <= #1 0; 
				imm_flag <= #1 0;
		end 
	endcase
	end
	//MUX for choose the 2s' compliment.
	mux2x1 m1(compliment2, REGOUT2, temp2, comp_flag);
	//MUX to choose immediate data or the regfile data.
	mux2x1 m2(INSTRUCTION[7:0], temp2, temp3, imm_flag);
	//ALU unit for the CPU
    alu alu1(REGOUT1, temp3, WRITEDATA, temp_sel);
    //reg_file reg2(WRITEDATA, REGOUT1, REGOUT2, INSTRUCTION[18:16], READREG1, READREG2, WRITE, CLK, RESET);
endmodule


module mux2x1(in1, in2, out, control);
	input [7:0] in1, in2;
	input control;
	output reg [7:0] out;
	always @(control, in1, in2)
	begin
		if(control)
		begin
		  out = in1;
		end else begin
		  out = in2;
		end
	end
endmodule


//Reset and update PC
module PC_reset(RESET, PC_0, CLK);
	input [31:0] PC_1;       //Next PC
	output reg [31:0] PC_0;  //Current PC
	input CLK, RESET;
	pc_adder add1(PC_0, PC_1); //Adding 4 for the current PC and store it in the next PC
	always @(posedge CLK)		//when a positive clk edge
	begin
	  if(RESET) begin			//If reset is 1, initialisse the current PC
	  	PC_0 = #1 0;
	  end else begin			//If reset == 0 , update next PC val to the current PC after a 1 time unit.
		PC_0 = #1 PC_1;
	  end
	end
endmodule

//for incrementing the PC
module pc_adder(PC_0, PC_1);
	input  [31:0] PC_0;
	output [31:0] PC_1;
	assign #1 PC_1 =  PC_0 +4;
endmodule

`include "alu_group09.v"			//Include the module ALU
`include "regfile_group09.v"		//Include the module regfile

group09_lab5_part3/cpu_wavedata.vcd
$date
	Wed Oct 28 11:07:29 2020
$end
$version
	Icarus Verilog
$end
$timescale
	1s
$end
$scope module cpu_tb $end
$scope module mycpu $end
$scope module reg1 $end
$var reg 8 ! \regfile[0] [7:0] $end
$upscope $end
$upscope $end
$upscope $end
$scope module cpu_tb $end
$scope module mycpu $end
$scope module reg1 $end
$var reg 8 " \regfile[1] [7:0] $end
$upscope $end
$upscope $end
$upscope $end
$scope module cpu_tb $end
$scope module mycpu $end
$scope module reg1 $end
$var reg 8 # \regfile[2] [7:0] $end
$upscope $end
$upscope $end
$upscope $end
$scope module cpu_tb $end
$scope module mycpu $end
$scope module reg1 $end
$var reg 8 $ \regfile[3] [7:0] $end
$upscope $end
$upscope $end
$upscope $end
$scope module cpu_tb $end
$scope module mycpu $end
$scope module reg1 $end
$var reg 8 % \regfile[4] [7:0] $end
$upscope $end
$upscope $end
$upscope $end
$scope module cpu_tb $end
$scope module mycpu $end
$scope module reg1 $end
$var reg 8 & \regfile[5] [7:0] $end
$upscope $end
$upscope $end
$upscope $end
$scope module cpu_tb $end
$scope module mycpu $end
$scope module reg1 $end
$var reg 8 ' \regfile[6] [7:0] $end
$upscope $end
$upscope $end
$upscope $end
$scope module cpu_tb $end
$scope module mycpu $end
$scope module reg1 $end
$var reg 8 ( \regfile[7] [7:0] $end
$upscope $end
$upscope $end
$upscope $end
$scope module cpu_tb $end
$var wire 32 ) PC [31:0] $end
$var wire 32 * INSTRUCTION [31:0] $end
$var reg 1 + CLK $end
$var reg 1 , RESET $end
$scope module mycpu $end
$var wire 1 + CLK $end
$var wire 32 - INSTRUCTION [31:0] $end
$var wire 1 , RESET $end
$var wire 8 . temp3 [7:0] $end
$var wire 8 / temp2 [7:0] $end
$var wire 3 0 opcode [2:0] $end
$var wire 8 1 compliment2 [7:0] $end
$var wire 8 2 WRITEDATA [7:0] $end
$var wire 8 3 REGOUT2 [7:0] $end
$var wire 8 4 REGOUT1 [7:0] $end
$var wire 32 5 PC [31:0] $end
$var reg 1 6 comp_flag $end
$var reg 1 7 imm_flag $end
$var reg 3 8 temp_sel [2:0] $end
$scope module alu1 $end
$var wire 3 9 SELECT [2:0] $end
$var wire 8 : orout [7:0] $end
$var wire 8 ; forwout [7:0] $end
$var wire 8 < andout [7:0] $end
$var wire 8 = addout [7:0] $end
$var wire 8 > RESULT [7:0] $end
$var wire 8 ? DATA2 [7:0] $end
$var wire 8 @ DATA1 [7:0] $end
$scope module a1 $end
$var wire 3 A SELECT [2:0] $end
$var wire 8 B RESULT [7:0] $end
$var wire 8 C DATA2 [7:0] $end
$var wire 8 D DATA1 [7:0] $end
$upscope $end
$scope module and1 $end
$var wire 8 E RESULT [7:0] $end
$var wire 3 F SELECT [2:0] $end
$var wire 8 G DATA2 [7:0] $end
$var wire 8 H DATA1 [7:0] $end
$upscope $end
$scope module f1 $end
$var wire 8 I RESULT [7:0] $end
$var wire 3 J SELECT [2:0] $end
$var wire 8 K DATA2 [7:0] $end
$upscope $end
$scope module m1 $end
$var wire 8 L in0 [7:0] $end
$var wire 8 M in1 [7:0] $end
$var wire 8 N in2 [7:0] $end
$var wire 3 O sel [2:0] $end
$var wire 8 P in3 [7:0] $end
$var reg 8 Q result [7:0] $end
$upscope $end
$scope module or1 $end
$var wire 8 R RESULT [7:0] $end
$var wire 3 S SELECT [2:0] $end
$var wire 8 T DATA2 [7:0] $end
$var wire 8 U DATA1 [7:0] $end
$upscope $end
$upscope $end
$scope module m1 $end
$var wire 1 6 control $end
$var wire 8 V in1 [7:0] $end
$var wire 8 W in2 [7:0] $end
$var reg 8 X out [7:0] $end
$upscope $end
$scope module m2 $end
$var wire 1 7 control $end
$var wire 8 Y in1 [7:0] $end
$var wire 8 Z in2 [7:0] $end
$var reg 8 [ out [7:0] $end
$upscope $end
$scope module reg1 $end
$var wire 1 + CLK $end
$var wire 8 \ IN [7:0] $end
$var wire 3 ] INADDRESS [2:0] $end
$var wire 8 ^ OUT1 [7:0] $end
$var wire 3 _ OUT1ADDRESS [2:0] $end
$var wire 8 ` OUT2 [7:0] $end
$var wire 3 a OUT2ADDRESS [2:0] $end
$var wire 1 , RESET $end
$var wire 1 b WRITE $end
$var integer 32 c i [31:0] $end
$upscope $end
$scope module res $end
$var wire 1 + CLK $end
$var wire 1 , RESET $end
$var wire 32 d PC_1 [31:0] $end
$var reg 32 e PC_0 [31:0] $end
$scope module add1 $end
$var wire 32 f PC_0 [31:0] $end
$var wire 32 g PC_1 [31:0] $end
$upscope $end
$upscope $end
$upscope $end
$upscope $end
$enddefinitions $end
#0
$dumpvars
bx g
bx f
bx e
bx d
b1000 c
1b
bx a
bx `
bx _
bx ^
bx ]
bx \
bx [
bx Z
bx Y
bx X
bx W
bx V
bx U
bx T
bx S
bx R
bx Q
bx P
bx O
bx N
bx M
bx L
bx K
bx J
bx I
bx H
bx G
bx F
bx E
bx D
bx C
bx B
bx A
bx @
bx ?
bx >
bx =
bx <
bx ;
bx :
bx 9
bx 8
x7
x6
bx 5
bx 4
bx 3
bx 2
bx 1
bx 0
bx /
bx .
bx -
1,
0+
bx *
bx )
bx (
bx '
bx &
bx %
bx $
bx #
bx "
bx !
$end
#4
1+
#5
b0 )
b0 5
b0 e
b0 f
b0 (
b0 '
b0 &
b0 %
b0 $
b0 #
b0 "
b0 !
b1000 c
0,
#6
b100 d
b100 g
#7
b0 0
b100 ]
b0 _
b101 a
b101 Y
b1000000000000000101 *
b1000000000000000101 -
#8
b101 .
b101 ?
b101 C
b101 G
b101 K
b101 T
b101 [
17
06
b0 8
b0 9
b0 A
b0 F
b0 J
b0 O
b0 S
0+
#9
b101 2
b101 >
b101 Q
b101 \
b0 /
b0 X
b0 Z
bx1x1 :
bx1x1 P
bx1x1 R
b0x0x <
b0x0x E
b0x0x N
b101 ;
b101 I
b101 L
b0 4
b0 @
b0 D
b0 H
b0 U
b0 ^
b0 3
b0 W
b0 `
#10
b101 :
b101 P
b101 R
b0 <
b0 E
b0 N
b0 1
b0 V
#11
b101 =
b101 B
b101 M
#12
1+
#13
b101 %
b100 )
b100 5
b100 e
b100 f
#14
b1000 d
b1000 g
#15
b1001 .
b1001 ?
b1001 C
b1001 G
b1001 K
b1001 T
b1001 [
b10 ]
b1 a
b1001 Y
b100000000000001001 *
b100000000000001001 -
#16
b1001 2
b1001 >
b1001 Q
b1001 \
b1001 :
b1001 P
b1001 R
b1001 ;
b1001 I
b1001 L
0+
#17
b1001 =
b1001 B
b1001 M
#20
1+
#21
b1000 )
b1000 5
b1000 e
b1000 f
b1001 #
#22
b1100 d
b1100 g
#23
b10 0
b10 .
b10 ?
b10 C
b10 G
b10 K
b10 T
b10 [
b110 ]
b100 _
b10 a
b10 Y
b10000001100000010000000010 *
b10000001100000010000000010 -
#24
b0 .
b0 ?
b0 C
b0 G
b0 K
b0 T
b0 [
07
b1 8
b1 9
b1 A
b1 F
b1 J
b1 O
b1 S
b1001 2
b1001 >
b1001 Q
b1001 \
b10 :
b10 P
b10 R
b10 ;
b10 I
b10 L
0+
#25
b1001 .
b1001 ?
b1001 C
b1001 G
b1001 K
b1001 T
b1001 [
b1001 /
b1001 X
b1001 Z
b0 :
b0 P
b0 R
b0 ;
b0 I
b0 L
b101 4
b101 @
b101 D
b101 H
b101 U
b101 ^
b1001 3
b1001 W
b1001 `
#26
b1 <
b1 E
b1 N
b1001 ;
b1001 I
b1001 L
b1101 :
b1101 P
b1101 R
b11110111 1
b11110111 V
#27
b1110 2
b1110 >
b1110 Q
b1110 \
b1110 =
b1110 B
b1110 M
#28
1+
#29
b1110 '
b1100 )
b1100 5
b1100 e
b1100 f
#30
b10000 d
b10000 g
#31
b1 0
b0 ]
b0 _
b110 a
b110 Y
b1000000000000000000000110 *
b1000000000000000000000110 -
#32
b1001 2
b1001 >
b1001 Q
b1001 \
b0 8
b0 9
b0 A
b0 F
b0 J
b0 O
b0 S
0+
#33
b1110 .
b1110 ?
b1110 C
b1110 G
b1110 K
b1110 T
b1110 [
b1110 /
b1110 X
b1110 Z
b0 4
b0 @
b0 D
b0 H
b0 U
b0 ^
b1110 3
b1110 W
b1110 `
#34
b1110 2
b1110 >
b1110 Q
b1110 \
b1110 ;
b1110 I
b1110 L
b1110 :
b1110 P
b1110 R
b0 <
b0 E
b0 N
b11110010 1
b11110010 V
#36
1+
#37
b10000 )
b10000 5
b10000 e
b10000 f
b1110 !
#38
b10100 d
b10100 g
#39
b0 0
b101 ]
b1 a
b1 Y
b1010000000000000001 *
b1010000000000000001 -
b1110 4
b1110 @
b1110 D
b1110 H
b1110 U
b1110 ^
#40
b1 .
b1 ?
b1 C
b1 G
b1 K
b1 T
b1 [
17
b1110 <
b1110 E
b1110 N
0+
#41
b1 2
b1 >
b1 Q
b1 \
b0 /
b0 X
b0 Z
b1111 :
b1111 P
b1111 R
b0 <
b0 E
b0 N
b1 ;
b1 I
b1 L
b0 3
b0 W
b0 `
#42
b0 1
b0 V
b1111 =
b1111 B
b1111 M
#44
1+
#45
b1 &
b10100 )
b10100 5
b10100 e
b10100 f
#46
b11000 d
b11000 g
#47
b11 0
b101 .
b101 ?
b101 C
b101 G
b101 K
b101 T
b101 [
b11 ]
b10 _
b101 a
b101 Y
b11000000110000001000000101 *
b11000000110000001000000101 -
#48
b0 .
b0 ?
b0 C
b0 G
b0 K
b0 T
b0 [
07
16
b1 8
b1 9
b1 A
b1 F
b1 J
b1 O
b1 S
b1111 2
b1111 >
b1111 Q
b1111 \
b100 <
b100 E
b100 N
b101 ;
b101 I
b101 L
0+
#49
b1110 :
b1110 P
b1110 R
b0 <
b0 E
b0 N
b0 ;
b0 I
b0 L
b1001 4
b1001 @
b1001 D
b1001 H
b1001 U
b1001 ^
b1 3
b1 W
b1 `
#50
b11111111 .
b11111111 ?
b11111111 C
b11111111 G
b11111111 K
b11111111 T
b11111111 [
b11111111 /
b11111111 X
b11111111 Z
b1001 :
b1001 P
b1001 R
b11111111 1
b11111111 V
#51
b11111111 :
b11111111 P
b11111111 R
b1001 <
b1001 E
b1001 N
b11111111 ;
b11111111 I
b11111111 L
#52
b1000 2
b1000 >
b1000 Q
b1000 \
b1000 =
b1000 B
b1000 M
1+
#53
b11000 )
b11000 5
b11000 e
b11000 f
b1000 $
#54
b11100 d
b11100 g
#55
bx 0
bx ]
bx _
bx a
bx Y
bx *
bx -
#56
0+
#57
bx 4
bx @
bx D
bx H
bx U
bx ^
bx 3
bx W
bx `
#58
bx .
bx ?
bx C
bx G
bx K
bx T
bx [
bx /
bx X
bx Z
bx <
bx E
bx N
bx 1
bx V
#59
bx 2
bx >
bx Q
bx \
bx :
bx P
bx R
bx ;
bx I
bx L
bx =
bx B
bx M
#60
1+
#61
b11100 )
b11100 5
b11100 e
b11100 f
#62
b100000 d
b100000 g
#64
0+
#68
1+
#69
b100000 )
b100000 5
b100000 e
b100000 f
#70
b100100 d
b100100 g
#72
0+
#76
1+
#77
b100100 )
b100100 5
b100100 e
b100100 f
#78
b101000 d
b101000 g
#80
0+
#84
1+
#85
b101000 )
b101000 5
b101000 e
b101000 f
#86
b101100 d
b101100 g
#88
0+
#92
1+
#93
b101100 )
b101100 5
b101100 e
b101100 f
#94
b110000 d
b110000 g
#96
0+
#100
1+
#101
b110000 )
b110000 5
b110000 e
b110000 f
#102
b110100 d
b110100 g
#104
0+
#108
1+
#109
b110100 )
b110100 5
b110100 e
b110100 f
#110
b111000 d
b111000 g
#112
0+
#116
1+
#117
b111000 )
b111000 5
b111000 e
b111000 f
#118
b111100 d
b111100 g
#120
0+
#124
1+
#125
b111100 )
b111100 5
b111100 e
b111100 f
#126
b1000000 d
b1000000 g
#128
0+
#132
1+
#133
b1000000 )
b1000000 5
b1000000 e
b1000000 f
#134
b1000100 d
b1000100 g
#136
0+
#140
1+
#141
b1000100 )
b1000100 5
b1000100 e
b1000100 f
#142
b1001000 d
b1001000 g
#144
0+
#148
1+
#149
b1001000 )
b1001000 5
b1001000 e
b1001000 f
#150
b1001100 d
b1001100 g
#152
0+
#156
1+
#157
b1001100 )
b1001100 5
b1001100 e
b1001100 f
#158
b1010000 d
b1010000 g
#160
0+
#164
1+
#165
b1010000 )
b1010000 5
b1010000 e
b1010000 f
#166
b1010100 d
b1010100 g
#168
0+
#172
1+
#173
b1010100 )
b1010100 5
b1010100 e
b1010100 f
#174
b1011000 d
b1011000 g
#176
0+
#180
1+
#181
b1011000 )
b1011000 5
b1011000 e
b1011000 f
#182
b1011100 d
b1011100 g
#184
0+
#188
1+
#189
b1011100 )
b1011100 5
b1011100 e
b1011100 f
#190
b1100000 d
b1100000 g
#192
0+
#196
1+
#197
b1100000 )
b1100000 5
b1100000 e
b1100000 f
#198
b1100100 d
b1100100 g
#200
0+
#204
1+
#205
b1100100 )
b1100100 5
b1100100 e
b1100100 f
