group09_lab5_part4/alu_group09.v
/*module test;
	reg signed  [7:0] op1,op2;
	reg [2:0] sel;
	wire signed  [7:0] out1,out2;
	wire zero;
	alu alu1(op1,op2,out1,zero,sel);
	initial
	begin
        sel=0;
        #5 sel=1;
        #5 sel=0;
        #3 sel=3;
        #15 sel=1;
        #5 sel=2;
        #5 sel=3;
        #2 sel=2;
	end
    initial
    begin
      op1=2;
      #7 op1=4;
      #15 op1=7;
      #9 op1=5;
    end
    initial
    begin
      op2=-5;
      #7 op2=2;
      #20 op2=8;
      #16 op2=6;
    end
	initial	
	$monitor($time," sel = %d op1 (%d), op2 (%d) = out %d, zero = %d",sel,op1,op2,out1, zero);
	initial
	begin
		$dumpfile("alu.vcd");
		$dumpvars(0,test);
	end	
endmodule
*/
module alu(DATA1,DATA2,RESULT,ZERO,SELECT);
	//Input port declaration
	//DATA 1, DATA2 8 bit inputs
	//SELECT 3 bit input
	input signed [7:0] DATA1,DATA2;
	input [2:0] SELECT;

	//Output port declatation
	//RESULT,forw,addition are 8 bit outputs
	//RESULT= final output of the ALU depending on the select input
	//forwout = output of forwardunit module
	//addout = output of addunit module
	//andout = output of andunit module
	//orout = output of orunit module
	output signed [7:0] RESULT,forwout,addout,andout,orout;
	output ZERO;

	//Instantiate all the functional units
	forwardunit f1(DATA2,SELECT,forwout);
	addunit a1(DATA1,DATA2,SELECT,addout);
	andunit and1(DATA1,DATA2,SELECT,andout);
	orunit or1(DATA1,DATA2,SELECT,orout);
	//To check the result is equal to 0.
	assign ZERO = ~RESULT[0] && ~RESULT[1] && ~RESULT[2] && ~RESULT[3] && ~RESULT[4] && ~RESULT[5] && ~RESULT[6] && ~RESULT[7];
	//Instantiate the mux to get the final output "RESULT"
	mux m1(forwout,addout,andout,orout,SELECT,RESULT);

endmodule
	
//FOWARD FUNCTION MODULE

module forwardunit(DATA2,SELECT,RESULT);
	//Input port declaration
	//DATA1,DATA2 - 8 bit signed inputs

	input [7:0] DATA2;
	input [2:0] SELECT;

	//Output port declaration
	//RESULT - 8 bit signed output = DATA2
	output  signed[7:0] RESULT;

	//Generate RESULT whenever DATA1 or DATA2 change
	//always @(SELECT,DATA2)
	 assign #1 RESULT=  DATA2;
 	
endmodule

//ADD FUNCTION MODULE

module addunit (DATA1,DATA2,SELECT,RESULT);
	//Input port declaration
	//DATA1,DATA2 - 8 bit signed inputs
	
	input signed [7:0] DATA1,DATA2;
	input [2:0] SELECT;

	//Output port declaration
	//RESULT - 8 bit signed output = DATA1 + DATA2
	output  signed [7:0] RESULT;
	
	//Generate RESULT whenever DATA1 or DATA2 change
	//always @(SELECT,DATA1,DATA2)
	 assign #2 RESULT =  ( DATA1 + DATA2) ;
endmodule

//AND FUNCTION MODULE

module andunit (DATA1,DATA2,SELECT,RESULT);
	//Input port declaration
	//DATA1,DATA2 - 8 bit signed inputs
	input signed [7:0] DATA1,DATA2;
	input [2:0] SELECT;

	//Output port declaration
	//RESULT - 8 bit signed output = DATA1 & DATA2
	output   [7:0] RESULT;
	
	//Generate RESULT whenever DATA1 or DATA2 change
	//always @(DATA1,DATA2)
	 assign #1 RESULT = ( DATA1 & DATA2) ;
endmodule

//OR FUNCTION MODULE

module orunit (DATA1,DATA2,SELECT,RESULT);
	//Input port declaration
	//DATA1,DATA2 - 8 bit signed inputs
	input signed [7:0] DATA1,DATA2;
	input [2:0] SELECT;
	
	//Output port declaration
	//RESULT - 8 bit signed output = DATA1 | DATA2
	output [7:0] RESULT;

	//Generate RESULT whenever DATA1 or DATA2 change
	//always @(DATA1,DATA2)
	assign #1 RESULT =  ( DATA1 | DATA2) ;
endmodule

	
//MULTIPLEXER MODULE (4 X 1)

module mux(in0,in1,in2,in3,sel,result);
	//Input port declaration
	//in0 = forwardunit output
	//in1 = addunit output
	//in2 = andunit output
	//in3 = orunit output
	//sel = 3 bit select input
	input signed [7:0] in0,in1,in2,in3;
	input [2:0] sel;

	//Output port declaration
	//result = final result of the mux depending on sel
	output reg signed[7:0] result;

	//Update the result whenever in0,in1,in2,in3 or sel change
	always @(in0,in1,in2,in3,sel)
	begin
		case (sel)
			3'b000:  result = in0;
			3'b001:  result = in1;
			3'b010:  result = in2;
			3'b011:  result = in3;
			default: result = -1;
			
		endcase
	end
endmodule

group09_lab5_part4/regfile_group09.v
//CO224 VERILOG LAB 5- PART 2
// 8 x 8 REGISTER FILE
//GROUP 09

//TOP LEVEL STIMULUS MODULE
/*
module test;
	//Input variable declaration
	//WRITEDATA = 8 Bit data input
	//WRITEREG = 3 bit write address
	//READREG1 & READREG2 = 3 bit read addresses
	//CLK = Clock signal
	//WRITEENABLE = Write enable signal (When WRITE =1 at positive clk edge) 
	//RESET = Reset registers signal (When RESET =1 at positive clk edge) 
	reg signed [7:0] WRITEDATA;
	reg [2:0] WRITEREG,READREG1,READREG2;
	reg CLK,WRITEENABLE,RESET;

	//Output variable declaration
	//REGOUT1 , REGOUT2 = 8 bit data stored in registers
	wire signed [7:0] REGOUT1,REGOUT2;
	
	//Monitor changes in variables
	initial 
	$monitor($time," CLK %d RESET %d WRITE %d OUT1ADDRESS %d OUT2ADDRESS %d OUT1=%d OUT2 = %d",CLK,RESET,WRITEENABLE,READREG1,READREG2,REGOUT1,REGOUT2);

	//Instantiate reg_file module
	reg_file r1(WRITEDATA,REGOUT1,REGOUT2,WRITEREG,READREG1,READREG2,WRITEENABLE,CLK,RESET);

	//Generate the CLK signal with period 10
	
	initial
	begin
		CLK=1'b1;
		forever #5 CLK =~CLK;
	end

	//Finish the simulation after 100 time units
	initial
	begin
		#100 $finish;
	end


        //WRITE VARIABLE
	initial
	begin
		WRITEENABLE = 0;
		#5 WRITEENABLE = 1;
	       	#40 WRITEENABLE = 0;
		#20 WRITEENABLE = 1;	
	
	end
	
	//RESET VARIABLE
	initial
	begin
		RESET = 1;
		#15 RESET = 0;
		#50 RESET = 1;
	        #10 RESET = 0;
	
	end

	//WRITING INPUTS (WRITEDATA AND WRITEREG)
	initial
	begin
		WRITEDATA = -23;
	       	WRITEREG = 3;
		#25;
		WRITEDATA = 35;
		WRITEREG = 6;
		#10;
		WRITEDATA = 20;
		WRITEREG = 2;
		#5
		WRITEDATA = 45;
		WRITEREG = 2;
		#20;
		WRITEDATA = 5;
		WRITEREG = 0;
		#25;
		WRITEDATA = 12;
		WRITEREG = 7;

	end

	//READING REGISTER VARIABLES
	initial
	begin
		READREG1 = 0;
		READREG2 = 3;
		#25;
	        READREG1 = 6;
		#10;
		READREG2 = 2;
		#20;
		READREG1 = 0;	
		#25;
		READREG2 = 7;
	
	end
	
	//Generate the wave file
	initial
	begin
		
		$dumpfile("reg.vcd");
		$dumpvars(0,test);
	end

endmodule


//REGISTER FILE MODULE
*/
module reg_file(IN,OUT1,OUT2,INADDRESS,OUT1ADDRESS,OUT2ADDRESS,WRITE,CLK,RESET);

	//INPUT PORT DECLARATION
	//IN = 8 bit write data
	//INADDRESS = 3 bit write address
	//OUT1ADDRESS, OUT2ADDRESS = 3 bit read addresses
	
	input signed [7:0] IN;
	input [2:0] INADDRESS,OUT1ADDRESS,OUT2ADDRESS;
	input CLK,WRITE,RESET;

	//OUTPUT PORT DECLARATION
	//OUT1,OUT2 = 8 bit read data
	output signed [7:0] OUT1,OUT2;
	
	//Register type array of 8 elements to store 8 bit register data
	reg signed [7:0] regfile [0:7];

	//Generate the wave file which includes the values stored in each register	
	//Implemented for testing purposes
	initial
	begin 
		$dumpfile("cpu_wavedata.vcd");
		for(i=0;i<8;i++)
			$dumpvars(1,regfile[i]);

	end
	initial
	begin
		#5;
		$display("\t\ttime\treg0\treg1\treg2\treg3\treg4\treg5\treg6\treg7");
		$display("\t\t--------------------------------------------------------------------------------");
		$monitor($time, "\t%d\t%d\t%d\t%d\t%d\t%d\t%d\t%d",regfile[0],regfile[1],regfile[2],regfile[3],regfile[4],regfile[5],regfile[6],regfile[7]);
	end

	//READ REGISTERS ASYNCHRONOUSLY
	//OUT1 AND OUT2 MUST CHANGE IF OUT1ADDRESS,OUT2ADDRESS OR THE VALUES IN RELEVANT REGISTERS CHANGE
	//OUT1 AND OUT2 MUST CHANGE AFTER A DELAY OF 2,UNTIL IT CHANGES IT SHOULD DISPLAY THE PREVIOUS VALUE STORED IN THEM
	//DELAY = 2
	assign #2 OUT1 =  regfile[OUT1ADDRESS];
	assign #2 OUT2 =  regfile[OUT2ADDRESS];
	//WRITE TO REGISTER AT THE POSITIVE EDGE OF CLK AND WHEN WRITE=1 AND RESET = 0
	//DELAY = 1
	always @(posedge CLK)
	begin
		if (WRITE && !RESET)
		/*begin
			regfile[INADDRESS] <= #1 IN;
		end*/
			#1 regfile[INADDRESS] =  IN;
	end
	 
	//RESET THE REGISTERS WHEN RESET=1 AND CLK IS IN POSITIVE EDGE
	//DELAY = 1
	integer i;
	always @(posedge CLK)
	begin
		if (RESET)
			#1
			begin
				for(i=0;i<8;i=i+1)
					/*begin
						regfile [i] <= #1 0;
					end*/
						regfile[i]  = 0;
			end
	end


endmodule

group09_lab5_part4/cpu_group09.v
//CO224 VERILOG LAB 5- PART 4
// CPU file
//GROUP 09


module cpu_tb;

    reg CLK, RESET;
    wire [31:0] PC;
    wire [31:0] INSTRUCTION;
    
    
    /* 
    ------------------------
     SIMPLE INSTRUCTION MEM
    ------------------------
    */
    
    //  Initialize an array of registers (8x1024) named 'instr_mem' to be used as instruction memory
    reg [7:0] instr_mem [0:1023];

    
    initial
    begin
        // Initialize instruction memory with the set of instructions you need execute on CPU
       
        // METHOD 2: loading instr_mem content from instr_mem.mem file
        $readmemb("instr_mem.mem", instr_mem);
    end
    // combinational logic to support CPU instruction fetching, given the Program Counter(PC) value 
       assign #2 INSTRUCTION ={instr_mem[PC+3] , instr_mem[PC+2] , instr_mem[PC+1],instr_mem[PC]};	
   /* -----
     CPU
    -----
    */
    cpu mycpu(PC, INSTRUCTION, CLK, RESET);

    initial
    begin
    
        // generate files needed to plot the waveform using GTKWave
        $dumpfile("cpu_wavedata.vcd");
		$dumpvars(0, cpu_tb);
        
        CLK = 1'b0;
        RESET = 1'b1;
	#5 RESET = 1'b0;
        
              
        // finish simulation after some time
        #300
        $finish;
        
    end
    
    // clock signal generation
    always
        #4 CLK = ~CLK;
        

endmodule

//CPU module
module cpu(PC, INSTRUCTION, CLK, RESET);
	//Input and output port decleration
   	input CLK, RESET;
    	input  [31:0] INSTRUCTION; //32 bit instruction.
    	output [31:0] PC;			//PC 32 bit address for the instruction memory.
    	//decleration of ports  to regfile and alu
    	input [7:0] WRITEDATA;
		input [2:0] READREG2,READREG1,WRITEREG;
    	input [3:0] opcode;
    	reg WRITE;
		wire ZERO;
    	output [7:0] REGOUT1, REGOUT2; 	//for regfile two outputs.
		output [7:0] temp2, temp3; 		//outputs for muxes.
		reg [2:0] temp_sel;				//for decoded output
		wire  pc_j, pc_b;               //select signals for muxes in the pc
		reg comp_flag, imm_flag,j_flag,b_flag; //select signals for complement mux(m1),immediate mux(m2), and branch and jump
		wire [7:0] compliment2;        //store the 2s complement of operand2

		output [31:0] PC_JUMP;   //pc_jump address
		wire [31:0] mux3out, mux4out;  //jump mux output and branch mux output
		input signed [7:0] OFFSET;   //jump offset
		assign OFFSET = INSTRUCTION[23:16];
		input [31:0] PC_1;       //Next PC


		//assigning the opcode,writereg,readregs.
		assign opcode = INSTRUCTION[31:24];
		assign WRITEREG = INSTRUCTION[23:16];
		assign READREG1 = INSTRUCTION[15:8];
		assign READREG2 = INSTRUCTION[7:0];


	//Calculating next pc
	pc_adder add1(PC, PC_1); //Adding 4 to the current PC and store it in the next PC
	jump_adder j1(PC_1, OFFSET, PC_JUMP);  //calculate the jump pc address
	mux2x1_32 m3(PC_JUMP, PC_1, mux3out, j_flag);  //select either pc+4 or pc_jump depending on jump flag
	mux2x1_32 m4(PC_JUMP, mux3out, mux4out, pc_b); //select either pc+4 or pc_jump depending on branch flag

		
	//reset or update the pc
	PC_reset res(RESET, PC, mux4out, CLK);
	//Instantiate the register.
   	reg_file reg1(WRITEDATA, REGOUT1, REGOUT2,WRITEREG,READREG1,READREG2, WRITE, CLK, RESET);
	//get the 2s complement of operand2
	assign #1 compliment2 =  ~REGOUT2 + 1;
	//Decoding the opcode and assiging select signals
	always @(opcode)
	begin
	case (opcode)
		4'b0000: {WRITE,temp_sel,comp_flag,imm_flag,b_flag,j_flag} = #1 8'b1_000_0_1_0_0; //loadi
		4'b0001: {WRITE,temp_sel,comp_flag,imm_flag,b_flag,j_flag} = #1 8'b1_000_0_0_0_0; //mov
		4'b0010: {WRITE,temp_sel,comp_flag,imm_flag,b_flag,j_flag} = #1 8'b1_001_0_0_0_0; //add
		4'b0011: {WRITE,temp_sel,comp_flag,imm_flag,b_flag,j_flag} = #1 8'b1_001_1_0_0_0; //sub
		4'b0100: {WRITE,temp_sel,comp_flag,imm_flag,b_flag,j_flag} = #1 8'b1_010_0_0_0_0; //and
		4'b0101: {WRITE,temp_sel,comp_flag,imm_flag,b_flag,j_flag} = #1 8'b1_011_0_0_0_0; //or
		4'b0110: {WRITE,comp_flag,imm_flag,b_flag,j_flag} 		   = #1 5'b0_0_0_0_1;     //jump
		4'b0111: {WRITE,temp_sel,comp_flag,imm_flag,b_flag,j_flag} = #1 8'b0_001_1_0_1_0; //beq
	endcase
	end
	//MUX for choose the 2s' compliment.
	mux2x1 m1(compliment2, REGOUT2, temp2, comp_flag);
	//MUX to choose immediate data or the regfile data.
	mux2x1 m2(INSTRUCTION[7:0], temp2, temp3, imm_flag);
	//ALU unit for the CPU
    alu alu1(REGOUT1, temp3, WRITEDATA, ZERO, temp_sel);
	//pc_b =1 if b_flag and zero are both 1(if a branch instruction is given and the operand1 and 2 are equal)
	assign pc_b = b_flag && ZERO;
	
   
endmodule

//8 bit 2x1 mux module to select immediate value and 2s complement
module mux2x1(in1, in2, out, control);
	input [7:0] in1, in2;
	input control;
	output reg [7:0] out;
	always @(control, in1, in2)
	begin
		if(control)
		begin
		  out = in1;
		end else begin
		  out = in2;
		end
	end
endmodule

//32 bit 2x1 mux module to select pc_jump or pc+4 value as the next pc
module mux2x1_32(in1, in2, out, control);
	input [31:0] in1, in2;
	input control;
	output reg [31:0] out;
	always @(control, in1, in2)
	begin
		if(control)
		begin
		  out = in1;
		end else begin
		  out = in2;
		end
	end
endmodule


//Reset and update PC
module PC_reset(RESET, PC_0, PC_1, CLK);
	input [31:0] PC_1;       //Next PC
	output reg [31:0] PC_0;  //Current PC
	input CLK, RESET, b_flag, j_flag; //select signals for branch mux(m4) and jump mux(m3)
	
	always @(posedge CLK)		//when a positive clk edge
	begin
	  if(RESET) begin			//If reset is 1, initialisse the current PC
	  	PC_0 = #1 0;
	  end else begin			//If reset == 0 , update next PC val to the current PC after a 1 time unit.
		#1 PC_0 =  PC_1;
	  end
	end
endmodule

//pc_jump adder
module jump_adder(PC_4, OFFSET, PC_JUMP);
	input [31:0] PC_4;
	output [31:0] PC_JUMP;
	input signed [7:0] OFFSET;
	wire [31:0] temp;
	assign temp = {{22{OFFSET[7]}}, OFFSET[7:0], {2{1'b0}}}; 
	assign #2 PC_JUMP = temp + PC_4;

endmodule

//for incrementing the PC
module pc_adder(PC_0, PC_1);
	input  [31:0] PC_0;
	output [31:0] PC_1;
	assign #1 PC_1 =  PC_0 +4;
endmodule

`include "alu_group09.v"			//Include the module ALU
`include "regfile_group09.v"		//Include the module regfile

group09_lab5_part4/cpu_wavedata.vcd
$date
	Wed Nov  4 10:07:40 2020
$end
$version
	Icarus Verilog
$end
$timescale
	1s
$end
$scope module cpu_tb $end
$scope module mycpu $end
$scope module reg1 $end
$var reg 8 ! \regfile[0] [7:0] $end
$upscope $end
$upscope $end
$upscope $end
$scope module cpu_tb $end
$scope module mycpu $end
$scope module reg1 $end
$var reg 8 " \regfile[1] [7:0] $end
$upscope $end
$upscope $end
$upscope $end
$scope module cpu_tb $end
$scope module mycpu $end
$scope module reg1 $end
$var reg 8 # \regfile[2] [7:0] $end
$upscope $end
$upscope $end
$upscope $end
$scope module cpu_tb $end
$scope module mycpu $end
$scope module reg1 $end
$var reg 8 $ \regfile[3] [7:0] $end
$upscope $end
$upscope $end
$upscope $end
$scope module cpu_tb $end
$scope module mycpu $end
$scope module reg1 $end
$var reg 8 % \regfile[4] [7:0] $end
$upscope $end
$upscope $end
$upscope $end
$scope module cpu_tb $end
$scope module mycpu $end
$scope module reg1 $end
$var reg 8 & \regfile[5] [7:0] $end
$upscope $end
$upscope $end
$upscope $end
$scope module cpu_tb $end
$scope module mycpu $end
$scope module reg1 $end
$var reg 8 ' \regfile[6] [7:0] $end
$upscope $end
$upscope $end
$upscope $end
$scope module cpu_tb $end
$scope module mycpu $end
$scope module reg1 $end
$var reg 8 ( \regfile[7] [7:0] $end
$upscope $end
$upscope $end
$upscope $end
$scope module cpu_tb $end
$var wire 32 ) PC [31:0] $end
$var wire 32 * INSTRUCTION [31:0] $end
$var reg 1 + CLK $end
$var reg 1 , RESET $end
$scope module mycpu $end
$var wire 1 + CLK $end
$var wire 32 - INSTRUCTION [31:0] $end
$var wire 1 , RESET $end
$var wire 1 . pc_b $end
$var wire 8 / temp3 [7:0] $end
$var wire 8 0 temp2 [7:0] $end
$var wire 4 1 opcode [3:0] $end
$var wire 32 2 mux4out [31:0] $end
$var wire 32 3 mux3out [31:0] $end
$var wire 8 4 compliment2 [7:0] $end
$var wire 1 5 ZERO $end
$var wire 3 6 WRITEREG [2:0] $end
$var wire 8 7 WRITEDATA [7:0] $end
$var wire 8 8 REGOUT2 [7:0] $end
$var wire 8 9 REGOUT1 [7:0] $end
$var wire 3 : READREG2 [2:0] $end
$var wire 3 ; READREG1 [2:0] $end
$var wire 32 < PC_JUMP [31:0] $end
$var wire 32 = PC_1 [31:0] $end
$var wire 32 > PC [31:0] $end
$var wire 8 ? OFFSET [7:0] $end
$var reg 1 @ WRITE $end
$var reg 1 A b_flag $end
$var reg 1 B comp_flag $end
$var reg 1 C imm_flag $end
$var reg 1 D j_flag $end
$var reg 3 E temp_sel [2:0] $end
$scope module add1 $end
$var wire 32 F PC_1 [31:0] $end
$var wire 32 G PC_0 [31:0] $end
$upscope $end
$scope module alu1 $end
$var wire 3 H SELECT [2:0] $end
$var wire 1 5 ZERO $end
$var wire 8 I orout [7:0] $end
$var wire 8 J forwout [7:0] $end
$var wire 8 K andout [7:0] $end
$var wire 8 L addout [7:0] $end
$var wire 8 M RESULT [7:0] $end
$var wire 8 N DATA2 [7:0] $end
$var wire 8 O DATA1 [7:0] $end
$scope module a1 $end
$var wire 3 P SELECT [2:0] $end
$var wire 8 Q RESULT [7:0] $end
$var wire 8 R DATA2 [7:0] $end
$var wire 8 S DATA1 [7:0] $end
$upscope $end
$scope module and1 $end
$var wire 8 T RESULT [7:0] $end
$var wire 3 U SELECT [2:0] $end
$var wire 8 V DATA2 [7:0] $end
$var wire 8 W DATA1 [7:0] $end
$upscope $end
$scope module f1 $end
$var wire 8 X RESULT [7:0] $end
$var wire 3 Y SELECT [2:0] $end
$var wire 8 Z DATA2 [7:0] $end
$upscope $end
$scope module m1 $end
$var wire 8 [ in0 [7:0] $end
$var wire 8 \ in1 [7:0] $end
$var wire 8 ] in2 [7:0] $end
$var wire 3 ^ sel [2:0] $end
$var wire 8 _ in3 [7:0] $end
$var reg 8 ` result [7:0] $end
$upscope $end
$scope module or1 $end
$var wire 8 a RESULT [7:0] $end
$var wire 3 b SELECT [2:0] $end
$var wire 8 c DATA2 [7:0] $end
$var wire 8 d DATA1 [7:0] $end
$upscope $end
$upscope $end
$scope module j1 $end
$var wire 8 e OFFSET [7:0] $end
$var wire 32 f PC_4 [31:0] $end
$var wire 32 g temp [31:0] $end
$var wire 32 h PC_JUMP [31:0] $end
$upscope $end
$scope module m1 $end
$var wire 1 B control $end
$var wire 8 i in1 [7:0] $end
$var wire 8 j in2 [7:0] $end
$var reg 8 k out [7:0] $end
$upscope $end
$scope module m2 $end
$var wire 1 C control $end
$var wire 8 l in1 [7:0] $end
$var wire 8 m in2 [7:0] $end
$var reg 8 n out [7:0] $end
$upscope $end
$scope module m3 $end
$var wire 1 D control $end
$var wire 32 o in1 [31:0] $end
$var wire 32 p in2 [31:0] $end
$var reg 32 q out [31:0] $end
$upscope $end
$scope module m4 $end
$var wire 1 . control $end
$var wire 32 r in1 [31:0] $end
$var wire 32 s in2 [31:0] $end
$var reg 32 t out [31:0] $end
$upscope $end
$scope module reg1 $end
$var wire 1 + CLK $end
$var wire 8 u IN [7:0] $end
$var wire 3 v INADDRESS [2:0] $end
$var wire 8 w OUT1 [7:0] $end
$var wire 3 x OUT1ADDRESS [2:0] $end
$var wire 8 y OUT2 [7:0] $end
$var wire 3 z OUT2ADDRESS [2:0] $end
$var wire 1 , RESET $end
$var wire 1 @ WRITE $end
$var integer 32 { i [31:0] $end
$upscope $end
$scope module res $end
$var wire 1 + CLK $end
$var wire 32 | PC_1 [31:0] $end
$var wire 1 , RESET $end
$var wire 1 } b_flag $end
$var wire 1 ~ j_flag $end
$var reg 32 !" PC_0 [31:0] $end
$upscope $end
$upscope $end
$upscope $end
$enddefinitions $end
#0
$dumpvars
bx !"
z~
z}
bx |
b1000 {
bx z
bx y
bx x
bx w
bx v
bx u
bx t
bx s
bx r
bx q
bx p
bx o
bx n
bx m
bx l
bx k
bx j
bx i
bx h
bx00 g
bx f
bx e
bx d
bx c
bx b
bx a
bx `
bx _
bx ^
bx ]
bx \
bx [
bx Z
bx Y
bx X
bx W
bx V
bx U
bx T
bx S
bx R
bx Q
bx P
bx O
bx N
bx M
bx L
bx K
bx J
bx I
bx H
bx G
bx F
bx E
xD
xC
xB
xA
x@
bx ?
bx >
bx =
bx <
bx ;
bx :
bx 9
bx 8
bx 7
bx 6
x5
bx 4
bx 3
bx 2
bx 1
bx 0
bx /
x.
bx -
1,
0+
bx *
bx )
bx (
bx '
bx &
bx %
bx $
bx #
bx "
bx !
$end
#4
1+
#5
b0 )
b0 >
b0 G
b0 !"
b0 (
b0 '
b0 &
b0 %
b0 $
b0 #
b0 "
b0 !
b1000 {
0,
#6
b100 2
b100 t
b100 |
b100 3
b100 q
b100 s
b100 =
b100 F
b100 f
b100 p
#7
b0 1
b100 6
b100 v
b0 ;
b0 x
b10 :
b10 z
b10000 g
b100 ?
b100 e
b1010 l
b1000000000000001010 *
b1000000000000001010 -
#8
b1010 /
b1010 N
b1010 R
b1010 V
b1010 Z
b1010 c
b1010 n
0.
1@
b0 E
b0 H
b0 P
b0 U
b0 Y
b0 ^
b0 b
0B
1C
0A
0D
0+
#9
05
b1010 7
b1010 M
b1010 `
b1010 u
b0 0
b0 k
b0 m
bx1x1x I
bx1x1x _
bx1x1x a
b0x0x0 K
b0x0x0 T
b0x0x0 ]
b1010 J
b1010 X
b1010 [
b10100 <
b10100 h
b10100 o
b10100 r
b0 9
b0 O
b0 S
b0 W
b0 d
b0 w
b0 8
b0 j
b0 y
#10
b1010 I
b1010 _
b1010 a
b0 K
b0 T
b0 ]
b0 4
b0 i
#11
b1010 L
b1010 Q
b1010 \
#12
1+
#13
b1010 %
b100 )
b100 >
b100 G
b100 !"
#14
b1000 2
b1000 t
b1000 |
b1000 3
b1000 q
b1000 s
b1000 =
b1000 F
b1000 f
b1000 p
#15
b101 6
b101 v
b1 :
b1 z
b1 /
b1 N
b1 R
b1 V
b1 Z
b1 c
b1 n
b10100 g
b101 ?
b101 e
b1 l
b1010000000000000001 *
b1010000000000000001 -
#16
b1 7
b1 M
b1 `
b1 u
b1 I
b1 _
b1 a
b1 J
b1 X
b1 [
0+
#17
b1 L
b1 Q
b1 \
b11100 <
b11100 h
b11100 o
b11100 r
#20
1+
#21
b1000 )
b1000 >
b1000 G
b1000 !"
b1 &
#22
b1100 2
b1100 t
b1100 |
b1100 3
b1100 q
b1100 s
b1100 =
b1100 F
b1100 f
b1100 p
#23
b110 6
b110 v
b11000 g
b110 ?
b110 e
b1100000000000000001 *
b1100000000000000001 -
#24
0+
#25
b100100 <
b100100 h
b100100 o
b100100 r
#28
1+
#29
b1 '
b1100 )
b1100 >
b1100 G
b1100 !"
#30
b10000 2
b10000 t
b10000 |
b10000 3
b10000 q
b10000 s
b10000 =
b10000 F
b10000 f
b10000 p
#31
b111 6
b111 v
b1001 /
b1001 N
b1001 R
b1001 V
b1001 Z
b1001 c
b1001 n
b11100 g
b111 ?
b111 e
b1001 l
b1110000000000001001 *
b1110000000000001001 -
#32
b1001 7
b1001 M
b1001 `
b1001 u
b1001 I
b1001 _
b1001 a
b1001 J
b1001 X
b1001 [
0+
#33
b1001 L
b1001 Q
b1001 \
b101100 <
b101100 h
b101100 o
b101100 r
#36
1+
#37
b10000 )
b10000 >
b10000 G
b10000 !"
b1001 (
#38
b10100 2
b10100 t
b10100 |
b10100 3
b10100 q
b10100 s
b10100 =
b10100 F
b10100 f
b10100 p
#39
b11 1
b100 6
b100 v
b100 ;
b100 x
b101 :
b101 z
b101 /
b101 N
b101 R
b101 V
b101 Z
b101 c
b101 n
b10000 g
b100 ?
b100 e
b101 l
b11000001000000010000000101 *
b11000001000000010000000101 -
#40
b0 /
b0 N
b0 R
b0 V
b0 Z
b0 c
b0 n
b1 E
b1 H
b1 P
b1 U
b1 Y
b1 ^
b1 b
1B
0C
b101 I
b101 _
b101 a
b101 J
b101 X
b101 [
0+
#41
b0 I
b0 _
b0 a
b0 J
b0 X
b0 [
b1010 9
b1010 O
b1010 S
b1010 W
b1010 d
b1010 w
b1 8
b1 j
b1 y
b100100 <
b100100 h
b100100 o
b100100 r
#42
b11111111 /
b11111111 N
b11111111 R
b11111111 V
b11111111 Z
b11111111 c
b11111111 n
b11111111 0
b11111111 k
b11111111 m
b1010 I
b1010 _
b1010 a
b11111111 4
b11111111 i
#43
b11111111 I
b11111111 _
b11111111 a
b1010 K
b1010 T
b1010 ]
b11111111 J
b11111111 X
b11111111 [
#44
1+
#45
b1001 %
b10100 )
b10100 >
b10100 G
b10100 !"
#46
b11000 2
b11000 t
b11000 |
b11000 3
b11000 q
b11000 s
b11000 =
b11000 F
b11000 f
b11000 p
#47
b111 1
b1 6
b1 v
b110 :
b110 z
b100 g
b1 ?
b1 e
b110 l
b1001 9
b1001 O
b1001 S
b1001 W
b1001 d
b1001 w
b111000000010000010000000110 *
b111000000010000010000000110 -
#48
0@
1A
b1001 K
b1001 T
b1001 ]
0+
#49
b1000 7
b1000 M
b1000 `
b1000 u
b11100 <
b11100 h
b11100 o
b11100 r
b1000 L
b1000 Q
b1000 \
#52
1+
#53
b11000 )
b11000 >
b11000 G
b11000 !"
#54
b11100 2
b11100 t
b11100 |
b11100 3
b11100 q
b11100 s
b11100 =
b11100 F
b11100 f
b11100 p
#55
b110 1
b101 6
b101 v
b0 ;
b0 x
b0 :
b0 z
b11111111111111111111111111110100 g
b11111101 ?
b11111101 e
b0 l
b110111111010000000000000000 *
b110111111010000000000000000 -
#56
b1 /
b1 N
b1 R
b1 V
b1 Z
b1 c
b1 n
b1 0
b1 k
b1 m
0B
0A
1D
0+
#57
b0 /
b0 N
b0 R
b0 V
b0 Z
b0 c
b0 n
b10000 2
b10000 t
b10000 |
b0 0
b0 k
b0 m
b10000 3
b10000 q
b10000 s
b1001 I
b1001 _
b1001 a
b1 K
b1 T
b1 ]
b1 J
b1 X
b1 [
b0 9
b0 O
b0 S
b0 W
b0 d
b0 w
b0 8
b0 j
b0 y
b10000 <
b10000 h
b10000 o
b10000 r
#58
b0 J
b0 X
b0 [
b0 I
b0 _
b0 a
b0 K
b0 T
b0 ]
b0 4
b0 i
#59
15
b0 7
b0 M
b0 `
b0 u
b0 L
b0 Q
b0 \
#60
1+
#61
b10000 )
b10000 >
b10000 G
b10000 !"
#62
b10100 =
b10100 F
b10100 f
b10100 p
#63
b11 1
b100 6
b100 v
b100 ;
b100 x
b101 :
b101 z
b10000 g
b100 ?
b100 e
b101 l
b11000001000000010000000101 *
b11000001000000010000000101 -
#64
b10100 2
b10100 t
b10100 |
b10100 3
b10100 q
b10100 s
1@
1B
0D
0+
#65
b1001 9
b1001 O
b1001 S
b1001 W
b1001 d
b1001 w
b1 8
b1 j
b1 y
b100100 <
b100100 h
b100100 o
b100100 r
#66
b11111111 /
b11111111 N
b11111111 R
b11111111 V
b11111111 Z
b11111111 c
b11111111 n
b11111111 0
b11111111 k
b11111111 m
b1001 I
b1001 _
b1001 a
b11111111 4
b11111111 i
#67
b11111111 I
b11111111 _
b11111111 a
b1001 K
b1001 T
b1001 ]
b11111111 J
b11111111 X
b11111111 [
#68
05
b1000 7
b1000 M
b1000 `
b1000 u
b1000 L
b1000 Q
b1000 \
1+
#69
b1000 %
b10100 )
b10100 >
b10100 G
b10100 !"
#70
b11000 2
b11000 t
b11000 |
b11000 3
b11000 q
b11000 s
b11000 =
b11000 F
b11000 f
b11000 p
#71
b111 1
b1 6
b1 v
b110 :
b110 z
b100 g
b1 ?
b1 e
b110 l
b1000 9
b1000 O
b1000 S
b1000 W
b1000 d
b1000 w
b111000000010000010000000110 *
b111000000010000010000000110 -
#72
0@
1A
b1000 K
b1000 T
b1000 ]
0+
#73
b111 7
b111 M
b111 `
b111 u
b11100 <
b11100 h
b11100 o
b11100 r
b111 L
b111 Q
b111 \
#76
1+
#77
b11000 )
b11000 >
b11000 G
b11000 !"
#78
b11100 2
b11100 t
b11100 |
b11100 3
b11100 q
b11100 s
b11100 =
b11100 F
b11100 f
b11100 p
#79
b110 1
b101 6
b101 v
b0 ;
b0 x
b0 :
b0 z
b11111111111111111111111111110100 g
b11111101 ?
b11111101 e
b0 l
b110111111010000000000000000 *
b110111111010000000000000000 -
#80
b1 /
b1 N
b1 R
b1 V
b1 Z
b1 c
b1 n
b1 0
b1 k
b1 m
0B
0A
1D
0+
